monosplit/__init__.py
monosplit/__main__.py
monosplit/split.py
tests/__init__.py
tests/test_pysplit.py
tests/data/testsplitfile.py
monosplit-0.1.2.dist-info/METADATA
monosplit-0.1.2.dist-info/WHEEL
monosplit-0.1.2.dist-info/entry_points.txt
monosplit-0.1.2.dist-info/top_level.txt
monosplit-0.1.2.dist-info/RECORD
