Metadata-Version: 2.1
Name: monosplit
Version: 0.1.2
Author-email: Grayson Miller <grayson.miller124@gmail.com>
Requires-Python: >=3.9
